stemmer/__init__.py
stemmer/stemmer_builder.py
bn_stemmer-1.0.0.dist-info/LICENSE
bn_stemmer-1.0.0.dist-info/METADATA
bn_stemmer-1.0.0.dist-info/WHEEL
bn_stemmer-1.0.0.dist-info/top_level.txt
bn_stemmer-1.0.0.dist-info/RECORD
