Metadata-Version: 2.1
Name: bn-stemmer
Version: 1.0.0
Summary: A Python package to stem bengali words
Home-page: https://github.com/ashwoolford/stemmer
Author: Ashraf H.
Author-email: asrafhossain197@gmail.com
License: MIT
Platform: UNKNOWN
Classifier: License :: OSI Approved :: MIT License
Classifier: Programming Language :: Python :: 3
